Verilog_project2/verilogcode/ring_counter_4bit.v
module ring_counter_4bit(
    input clk,
    input rst,
    output reg [3:0] q
);

always @(posedge clk or posedge rst)
begin
    if(rst)
        q <= 4'b0001;
    else
        q <= {q[2:0], q[3]};
end

endmodule

Verilog_project2/tb/tb_ring_counter_4bit.v
module tb_ring_counter_4bit;

reg clk;
reg rst;

wire [3:0] q;

ring_counter_4bit uut(
    .clk(clk),
    .rst(rst),
    .q(q)
);

initial begin
    clk = 0;
    forever #5 clk = ~clk;
end

initial begin

    $dumpfile("ring_counter.vcd");
    $dumpvars(0,tb_ring_counter_4bit);

    rst = 1;
    #10;

    rst = 0;
    #100;
    $finish;

end

endmodule

Verilog_project2/ring_counter.vcd
$date
	Thu Jul 16 07:46:24 2026
$end
$version
	Icarus Verilog
$end
$timescale
	1s
$end
$scope module tb_ring_counter_4bit $end
$var wire 4 ! q [3:0] $end
$var reg 1 " clk $end
$var reg 1 # rst $end
$scope module uut $end
$var wire 1 " clk $end
$var wire 1 # rst $end
$var reg 4 $ q [3:0] $end
$upscope $end
$upscope $end
$enddefinitions $end
$comment Show the parameter values. $end
$dumpall
$end
#0
$dumpvars
b1 $
1#
0"
b1 !
$end
#5
1"
#10
0"
0#
#15
b10 !
b10 $
1"
#20
0"
#25
b100 !
b100 $
1"
#30
0"
#35
b1000 !
b1000 $
1"
#40
0"
#45
b1 !
b1 $
1"
#50
0"
#55
b10 !
b10 $
1"
#60
0"
#65
b100 !
b100 $
1"
#70
0"
#75
b1000 !
b1000 $
1"
#80
0"
#85
b1 !
b1 $
1"
#90
0"
#95
b10 !
b10 $
1"
#100
0"
#105
b100 !
b100 $
1"
